{ "words" :

    {
        "falls" : {"definition" : " " },

        "features" : {"definition" : " " },

        "celebrations" : {"definition" : " " },

        "celebrates" : {"definition" : " " },

        "is celebrated" : {"definition" : " " },

        "celebratory" : {"definition" : " " },

        "festive" : {"definition" : " " },

        "festival" : {"definition" : " " },

        "festivities" : {"definition" : " " },

        "parade" : {"definition" : " " },

        "spectacle" : {"definition" : " " },

        "paraded" : {"definition" : " " },

        "spectacular" : {"definition" : " " },

        "feasting" : {"definition" : " " },

        "feast" : {"definition" : " " },

        "ceremonies" : {"definition" : " " },

        "ceremonial" : {"definition" : " " },

        "renewal" : {"definition" : " " },

        "renews" : {"definition" : " " },

        "renewed" : {"definition" : " " },

        "superstitious" : {"definition" : " " },

        "centenary" : {"definition" : " " },

        "bi-centenary" : {"definition" : " " },

        "flamboyant" : {"definition" : " " },

        "raucous" : {"definition" : " " },

        "sombre" : {"definition" : " " },

        "atmospheric" : {"definition" : " " },

        "traced back to pagan times" : {"definition" : " " },

        "commemorates" : {"definition" : " " }

    }
}