{ "words" :

    {
        "lobby" : {"definition" : " " },

        "petition" : {"definition" : " " },

        "legislation" : {"definition" : " " },

        "committee stage" : {"definition" : " " },

        "bill" : {"definition" : " " },

        "select committee" : {"definition" : " " },

        "scrutinising" : {"definition" : " " },

        "briefing" : {"definition" : " " },

        "rallies" : {"definition" : " " },

        "ultimately" : {"definition" : " " },

        "down to" : {"definition" : " " },

        "set out" : {"definition" : " " },

        "Hansard" : {"definition" : " " },

        "present" : {"definition" : " " },

        "constituents" : {"definition" : " " },

        "Speaker's" : {"definition" : " " },

        "observations" : {"definition" : " " },

        "substantive" : {"definition" : " " },

        "constituency" : {"definition" : " " },

        "policies" : {"definition" : " " },

        "Environmental Audit" : {"definition" : " " },

        "allegations" : {"definition" : " " },

        "conduct" : {"definition" : " " },

        "shadow" : {"definition" : " " },

        "wide-ranging" : {"definition" : " " },

        "expertise" : {"definition" : " " },

        "constitution" : {"definition" : " " },
        
        "crosses demartmental boundaries" : {"definition" : " " }

    }
}