{ "words" :

    {
        "roadworthy" : {"definition" : " " },

        "give way" : {"definition" : " " },

        "the right of way" : {"definition" : " " },

        "sounding" : {"definition" : " " },

        "beeping" : {"definition" : " " },

        "jumping" : {"definition" : " " },

        "reckless" : {"definition" : " " },

        "crossing" : {"definition" : " " },

        "drink-driving" : {"definition" : " " },

        "on-the-spot" : {"definition" : " " },

        "exhaust emissions" : {"definition" : " " },

        "tyre tread" : {"definition" : " " },

        "drug-driving" : {"definition" : " " },

        "breathalyser" : {"definition" : " " },

        "a ban" : {"definition" : " " },

        "penalty points" : {"definition" : " " },

        "bald" : {"definition" : " " },

        "hit-and-run" : {"definition" : " " },

        "clamped" : {"definition" : " " },

        "road rage" : {"definition" : " " },

        "tailback" : {"definition" : " " },

        "congestion" : {"definition" : " " },

        "congestion charge" : {"definition" : " " },

        "toll" : {"definition" : " " },

        "pile-up" : {"definition" : " " },

        "diverted" : {"definition" : " " },

        "disruption" : {"definition" : " " },

        "tow-away zone" : {"definition" : " " },

        "skidded" : {"definition" : " " },

        "head-on collision" : {"definition" : " " }

    }
}