{ "words" :

    {
        "Christmas" : {"definition" : " " },

        "New Year's Eve" : {"definition" : " " },

        "New Year's Day" : {"definition" : " " },

        "Valentine's Day" : {"definition" : " " },

        "Easter" : {"definition" : " " },

        "Halloween" : {"definition" : " " },

        "Bonfire Night" : {"definition" : " " },

        "fireworks" : {"definition" : " " },

        "Easter eggs" : {"definition" : " " },

        "bank holiday" : {"definition" : " " },

        "Christmas tree" : {"definition" : " " },

        "fish" : {"definition" : " " },

        "chips" : {"definition" : " " },

        "roast beef" : {"definition" : " " },

        "roast potatoes" : {"definition" : " " },

        "oven" : {"definition" : " " },

        "Yorkshire pudding" : {"definition" : " " },

        "Chicken tikka masala" : {"definition" : " " },

        "curry" : {"definition" : " " },

        "nursery school" : {"definition" : " " },

        "primary school" : {"definition" : " " },

        "secondary school" : {"definition" : " " },

        "state school" : {"definition" : " " },

        "private school" : {"definition" : " " },

        "royal family" : {"definition" : " " },

        "king" : {"definition" : " " },

        "queen" : {"definition" : " " },

        "Houses of Parliament" : {"definition" : " " },

        "Prime Minister" : {"definition" : " " }

    }
}