{ "words" :

    {
        "check your email" : {"definition" : " " },

        "essential" : {"definition" : " " },

        "immediately" : {"definition" : " " },

        "reply to" : {"definition" : " " },

        "delete" : {"definition" : " " },

        "regularly" : {"definition" : " " },

        "spam" : {"definition" : " " },

        "anti-virus software" : {"definition" : " " },

        "attachments" : {"definition" : " " },

        "on the Internet" : {"definition" : " " },

        "ISP" : {"definition" : " " },

        "connect" : {"definition" : " " },

        "access to" : {"definition" : " " },

        "browse" : {"definition" : " " },

        "go online" : {"definition" : " " },

        "browser" : {"definition" : " " },

        "click" : {"definition" : " " },

        "websites" : {"definition" : " " },

        "links" : {"definition" : " " },

        "access" : {"definition" : " " },

        "search" : {"definition" : " " },

        "download" : {"definition" : " " },

        "upload" : {"definition" : " " },

        "video clips" : {"definition" : " " },

        "item" : {"definition" : " " },

        "add to basket" : {"definition" : " " },

        "checkout" : {"definition" : " " },

        "blogs" : {"definition" : " " },

        "bloggers" : {"definition" : " " },

        "surfing the web" : {"definition" : " " },

        "social networking sites" : {"definition" : " " },

        "instant messaging" : {"definition" : " " },

        "post" : {"definition" : " " }

    }
}