{ "words" :

    {
        "objects" : {"definition" : " " },

        "materials" : {"definition" : " " },

        "bell" : {"definition" : " " },

        "metal" : {"definition" : " " },

        "antique" : {"definition" : " " },

        "real" : {"definition" : " " },

        "bone" : {"definition" : " " },

        "rubber" : {"definition" : " " },

        "toy" : {"definition" : " " },

        "flag" : {"definition" : " " },

        "national" : {"definition" : " " },

        "cotton" : {"definition" : " " },

        "stripes" : {"definition" : " " },

        "silk" : {"definition" : " " },

        "leather" : {"definition" : " " },

        "stylish" : {"definition" : " " },

        "ladder" : {"definition" : " " },

        "tissue" : {"definition" : " " },

        "bucket" : {"definition" : " " },

        "plastic" : {"definition" : " " },

        "wooden" : {"definition" : " " },

        "a grey square" : {"definition" : " " },

        "a pink star" : {"definition" : " " },

        "a navy blue circle" : {"definition" : " " },

        "a green semi-circle" : {"definition" : " " },

        "a purple heart" : {"definition" : " " },

        "a round" : {"definition" : " " },

        "a square" : {"definition" : " " },

        "pointed" : {"definition" : " " },

        "roundish" : {"definition" : " " },

        "greenish" : {"definition" : " " }

    }
}