{ "words" :

    {
        "appearance" : {"definition" : " " },

        "beauty" : {"definition" : " " },

        "attractive" : {"definition" : " " },

        "good-looking" : {"definition" : " " },

        "pretty" : {"definition" : " " },

        "gorgeous" : {"definition" : " " },

        "handsome" : {"definition" : " " },

        "ordinary" : {"definition" : " " },

        "ugly" : {"definition" : " " },

        "overweight" : {"definition" : " " },

        "height" : {"definition" : " " },

        "weight" : {"definition" : " " },

        "roughly" : {"definition" : " " },

        "approximately" : {"definition" : " " },

        "average" : {"definition" : " " },

        "blonde" : {"definition" : " " },

        "fair" : {"definition" : " " },

        "brown" : {"definition" : " " },

        "dark" : {"definition" : " " },

        "black" : {"definition" : " " },

        "straight" : {"definition" : " " },

        "wavy" : {"definition" : " " },

        "curly" : {"definition" : " " },

        "hair" : {"definition" : " " },

        "What does she look like?" : {"definition" : " " },

        "tallish" : {"definition" : " " },

        "broad" : {"definition" : " " },

        "narrow" : {"definition" : " " },

        "athletic" : {"definition" : " " },

        "smart" : {"definition" : " " },

        "dres" : {"definition" : " " },

        "well" : {"definition" : " " },

        "longish" : {"definition" : " " }
    }
}