{ "words" :

    {
        "because" : {"definition" : " " },

        "since" : {"definition" : " " },

        "as" : {"definition" : " " },

        "cause" : {"definition" : " " },

        "reason" : {"definition" : " " },

        "due to" : {"definition" : " " },

        "was caused by" : {"definition" : " " },

        "the cause of" : {"definition" : " " },

        "cause to" : {"definition" : " " },

        "owing to" : {"definition" : " " },

        "owing to the fact that" : {"definition" : " " },

        "sparked off" : {"definition" : " " },

        "give rise to" : {"definition" : " " },

        "provoked" : {"definition" : " " },

        "generated" : {"definition" : " " },

        "brought about" : {"definition" : " " },

        "led to" : {"definition" : " " },

        "stems from" : {"definition" : " " },

        "arose from" : {"definition" : " " },

        "reason for" : {"definition" : " " },

        "the reason why" : {"definition" : " " },

        "motives in" : {"definition" : " " },

        "prompted" : {"definition" : " " },
        
        "with the aim of" : {"definition" : " " },

        "with a view to" : {"definition" : " " },

        "on the grounds that" : {"definition" : " " },

        "the pupose of" : {"definition" : " " },

        "as a result" : {"definition" : " " },

        "as a consequence" : {"definition" : " " },

        "consequently" : {"definition" : " " },

        "outcome" : {"definition" : " " },

        "upshot" : {"definition" : " " },

        "ensued" : {"definition" : " " }

    }
}